pictograph/__init__.py
pictograph/client.py
pictograph/exceptions.py
pictograph/http_client.py
pictograph/resources/__init__.py
pictograph/resources/annotations.py
pictograph/resources/api_keys.py
pictograph/resources/datasets.py
pictograph/resources/exports.py
pictograph/resources/images.py
pictograph-0.1.10.dist-info/LICENSE
pictograph-0.1.10.dist-info/METADATA
pictograph-0.1.10.dist-info/WHEEL
pictograph-0.1.10.dist-info/top_level.txt
pictograph-0.1.10.dist-info/RECORD
