Metadata-Version: 2.1
Name: pictograph
Version: 0.1.10
Summary: Official Python SDK for Pictograph Context Engine - Computer Vision Annotation Platform
Home-page: https://pictograph.cloud
Author: Pictograph
Author-email: Pictograph <support@pictograph.cloud>
Project-URL: Homepage, https://pictograph.cloud
Project-URL: Documentation, https://pictograph.cloud/docs
Project-URL: Repository, https://github.com/pictograph-labs/pictograph-sdk
Project-URL: Bug Tracker, https://github.com/pictograph-labs/pictograph-sdk/issues
Keywords: computer-vision,annotation,labeling,dataset,machine-learning,ai
Classifier: Development Status :: 4 - Beta
Classifier: Intended Audience :: Developers
Classifier: Programming Language :: Python :: 3
Classifier: Programming Language :: Python :: 3.8
Classifier: Programming Language :: Python :: 3.9
Classifier: Programming Language :: Python :: 3.10
Classifier: Programming Language :: Python :: 3.11
Classifier: Programming Language :: Python :: 3.12
Classifier: Topic :: Software Development :: Libraries :: Python Modules
Classifier: Topic :: Scientific/Engineering :: Artificial Intelligence
Classifier: Topic :: Scientific/Engineering :: Image Recognition
Requires-Python: >=3.8
License-File: LICENSE
Requires-Dist: requests>=2.31.0
Requires-Dist: Pillow>=10.0.0
Requires-Dist: tqdm>=4.65.0
Provides-Extra: dev
Requires-Dist: pytest>=7.0.0; extra == "dev"
Requires-Dist: pytest-cov>=4.0.0; extra == "dev"
Requires-Dist: black>=23.0.0; extra == "dev"
Requires-Dist: mypy>=1.0.0; extra == "dev"
Requires-Dist: flake8>=6.0.0; extra == "dev"
